{
  "version": "0.0.1",
  "metrics": [
    {
      "capture_id": null,
      "annotation_id": null,
      "sequence_id": "f2ddd0f9-3140-4c48-8607-5c32061c88c1",
      "step": 0,
      "metric_definition": "db1b258e-d1d0-41b6-8751-16f601a2e230",
      "values": [
        {
          "iteration": 5399
        }
      ]
    },
    {
      "capture_id": null,
      "annotation_id": null,
      "sequence_id": "82bd711e-de55-4901-a5e8-7a57287f68cc",
      "step": 0,
      "metric_definition": "db1b258e-d1d0-41b6-8751-16f601a2e230",
      "values": [
        {
          "iteration": 5400
        }
      ]
    },
    {
      "capture_id": null,
      "annotation_id": null,
      "sequence_id": "cba4144b-9cec-4570-9121-9c81885cd8b5",
      "step": 0,
      "metric_definition": "db1b258e-d1d0-41b6-8751-16f601a2e230",
      "values": [
        {
          "iteration": 5401
        }
      ]
    },
    {
      "capture_id": null,
      "annotation_id": null,
      "sequence_id": "bd9fd94b-a84c-491a-a87d-761436553f28",
      "step": 0,
      "metric_definition": "db1b258e-d1d0-41b6-8751-16f601a2e230",
      "values": [
        {
          "iteration": 5402
        }
      ]
    },
    {
      "capture_id": null,
      "annotation_id": null,
      "sequence_id": "e5e94ee9-f7bc-457c-bd2c-2f36f0bd596a",
      "step": 0,
      "metric_definition": "db1b258e-d1d0-41b6-8751-16f601a2e230",
      "values": [
        {
          "iteration": 5403
        }
      ]
    },
    {
      "capture_id": null,
      "annotation_id": null,
      "sequence_id": "fa6642dd-24d8-4aae-9afd-254811656362",
      "step": 0,
      "metric_definition": "db1b258e-d1d0-41b6-8751-16f601a2e230",
      "values": [
        {
          "iteration": 5404
        }
      ]
    },
    {
      "capture_id": null,
      "annotation_id": null,
      "sequence_id": "edba9ed4-0242-4dfa-8403-eaa479d3b2d6",
      "step": 0,
      "metric_definition": "db1b258e-d1d0-41b6-8751-16f601a2e230",
      "values": [
        {
          "iteration": 5405
        }
      ]
    },
    {
      "capture_id": null,
      "annotation_id": null,
      "sequence_id": "ba12b8d5-017b-4672-be81-7a0b3563da95",
      "step": 0,
      "metric_definition": "db1b258e-d1d0-41b6-8751-16f601a2e230",
      "values": [
        {
          "iteration": 5406
        }
      ]
    },
    {
      "capture_id": null,
      "annotation_id": null,
      "sequence_id": "d4745013-bc9b-4ce2-8d41-ee2e4aae1793",
      "step": 0,
      "metric_definition": "db1b258e-d1d0-41b6-8751-16f601a2e230",
      "values": [
        {
          "iteration": 5407
        }
      ]
    },
    {
      "capture_id": null,
      "annotation_id": null,
      "sequence_id": "67921d0c-164e-4483-aa4d-186a3c4721e5",
      "step": 0,
      "metric_definition": "db1b258e-d1d0-41b6-8751-16f601a2e230",
      "values": [
        {
          "iteration": 5408
        }
      ]
    },
    {
      "capture_id": null,
      "annotation_id": null,
      "sequence_id": "569463a0-eb85-4018-9573-15cc7fcb695b",
      "step": 0,
      "metric_definition": "db1b258e-d1d0-41b6-8751-16f601a2e230",
      "values": [
        {
          "iteration": 5409
        }
      ]
    },
    {
      "capture_id": null,
      "annotation_id": null,
      "sequence_id": "b43b595f-54eb-40c8-8b5d-77dbf4234284",
      "step": 0,
      "metric_definition": "db1b258e-d1d0-41b6-8751-16f601a2e230",
      "values": [
        {
          "iteration": 5410
        }
      ]
    },
    {
      "capture_id": null,
      "annotation_id": null,
      "sequence_id": "c533c67e-78ff-4712-b64f-b19e21697ae9",
      "step": 0,
      "metric_definition": "db1b258e-d1d0-41b6-8751-16f601a2e230",
      "values": [
        {
          "iteration": 5411
        }
      ]
    },
    {
      "capture_id": null,
      "annotation_id": null,
      "sequence_id": "4598277d-61c6-48b3-8a63-6e733ee020b6",
      "step": 0,
      "metric_definition": "db1b258e-d1d0-41b6-8751-16f601a2e230",
      "values": [
        {
          "iteration": 5412
        }
      ]
    },
    {
      "capture_id": null,
      "annotation_id": null,
      "sequence_id": "5f9e1712-8643-4553-853d-bff468802ded",
      "step": 0,
      "metric_definition": "db1b258e-d1d0-41b6-8751-16f601a2e230",
      "values": [
        {
          "iteration": 5413
        }
      ]
    },
    {
      "capture_id": null,
      "annotation_id": null,
      "sequence_id": "c2ab846d-e35c-4567-bd01-acccc5f73b7e",
      "step": 0,
      "metric_definition": "db1b258e-d1d0-41b6-8751-16f601a2e230",
      "values": [
        {
          "iteration": 5414
        }
      ]
    },
    {
      "capture_id": null,
      "annotation_id": null,
      "sequence_id": "1a9e8cac-f4ac-4413-bc58-b9b10838c415",
      "step": 0,
      "metric_definition": "db1b258e-d1d0-41b6-8751-16f601a2e230",
      "values": [
        {
          "iteration": 5415
        }
      ]
    },
    {
      "capture_id": null,
      "annotation_id": null,
      "sequence_id": "ddd76e04-e448-46d1-83d7-927adf72f01a",
      "step": 0,
      "metric_definition": "db1b258e-d1d0-41b6-8751-16f601a2e230",
      "values": [
        {
          "iteration": 5416
        }
      ]
    },
    {
      "capture_id": null,
      "annotation_id": null,
      "sequence_id": "5ad47638-72eb-4f25-85e2-01566cb3b93e",
      "step": 0,
      "metric_definition": "db1b258e-d1d0-41b6-8751-16f601a2e230",
      "values": [
        {
          "iteration": 5417
        }
      ]
    },
    {
      "capture_id": null,
      "annotation_id": null,
      "sequence_id": "2b847913-8048-498e-8391-daf0f2aafa25",
      "step": 0,
      "metric_definition": "db1b258e-d1d0-41b6-8751-16f601a2e230",
      "values": [
        {
          "iteration": 5418
        }
      ]
    },
    {
      "capture_id": null,
      "annotation_id": null,
      "sequence_id": "d636217a-e7cd-4d8f-9a27-0555bbe91215",
      "step": 0,
      "metric_definition": "db1b258e-d1d0-41b6-8751-16f601a2e230",
      "values": [
        {
          "iteration": 5419
        }
      ]
    },
    {
      "capture_id": null,
      "annotation_id": null,
      "sequence_id": "21d25c95-7894-4452-ab2d-405b286e0830",
      "step": 0,
      "metric_definition": "db1b258e-d1d0-41b6-8751-16f601a2e230",
      "values": [
        {
          "iteration": 5420
        }
      ]
    },
    {
      "capture_id": null,
      "annotation_id": null,
      "sequence_id": "fb5a9a7c-edde-44f7-9192-00130e118b04",
      "step": 0,
      "metric_definition": "db1b258e-d1d0-41b6-8751-16f601a2e230",
      "values": [
        {
          "iteration": 5421
        }
      ]
    },
    {
      "capture_id": null,
      "annotation_id": null,
      "sequence_id": "417ecf22-a3db-4858-844f-143ed0daba64",
      "step": 0,
      "metric_definition": "db1b258e-d1d0-41b6-8751-16f601a2e230",
      "values": [
        {
          "iteration": 5422
        }
      ]
    },
    {
      "capture_id": null,
      "annotation_id": null,
      "sequence_id": "0f8396f3-edfc-40a1-b901-9062299cd31c",
      "step": 0,
      "metric_definition": "db1b258e-d1d0-41b6-8751-16f601a2e230",
      "values": [
        {
          "iteration": 5423
        }
      ]
    },
    {
      "capture_id": null,
      "annotation_id": null,
      "sequence_id": "224fac3b-06ed-4bdb-93fe-109280392bb4",
      "step": 0,
      "metric_definition": "db1b258e-d1d0-41b6-8751-16f601a2e230",
      "values": [
        {
          "iteration": 5424
        }
      ]
    },
    {
      "capture_id": null,
      "annotation_id": null,
      "sequence_id": "c1093d07-d810-49c4-8f1a-05fc75eba694",
      "step": 0,
      "metric_definition": "db1b258e-d1d0-41b6-8751-16f601a2e230",
      "values": [
        {
          "iteration": 5425
        }
      ]
    },
    {
      "capture_id": null,
      "annotation_id": null,
      "sequence_id": "7fc87c23-a908-4099-b505-9513dd3747f0",
      "step": 0,
      "metric_definition": "db1b258e-d1d0-41b6-8751-16f601a2e230",
      "values": [
        {
          "iteration": 5426
        }
      ]
    },
    {
      "capture_id": null,
      "annotation_id": null,
      "sequence_id": "ee7bdb70-0c1d-44bf-9c55-7d1a4d3f7d8e",
      "step": 0,
      "metric_definition": "db1b258e-d1d0-41b6-8751-16f601a2e230",
      "values": [
        {
          "iteration": 5427
        }
      ]
    },
    {
      "capture_id": null,
      "annotation_id": null,
      "sequence_id": "bcb60020-37e7-4c41-a57b-58852b4554c4",
      "step": 0,
      "metric_definition": "db1b258e-d1d0-41b6-8751-16f601a2e230",
      "values": [
        {
          "iteration": 5428
        }
      ]
    },
    {
      "capture_id": null,
      "annotation_id": null,
      "sequence_id": "4c5ed1e8-d245-4d0e-b1ef-df857cab0d2d",
      "step": 0,
      "metric_definition": "db1b258e-d1d0-41b6-8751-16f601a2e230",
      "values": [
        {
          "iteration": 5429
        }
      ]
    },
    {
      "capture_id": null,
      "annotation_id": null,
      "sequence_id": "c66731ee-9d97-4c2e-b716-17e213d093bc",
      "step": 0,
      "metric_definition": "db1b258e-d1d0-41b6-8751-16f601a2e230",
      "values": [
        {
          "iteration": 5430
        }
      ]
    },
    {
      "capture_id": null,
      "annotation_id": null,
      "sequence_id": "6d700ec9-db30-4266-bc8c-9997ea726981",
      "step": 0,
      "metric_definition": "db1b258e-d1d0-41b6-8751-16f601a2e230",
      "values": [
        {
          "iteration": 5431
        }
      ]
    },
    {
      "capture_id": null,
      "annotation_id": null,
      "sequence_id": "3dfd8fdd-401e-4e27-ab4a-fe3bc3b99bd1",
      "step": 0,
      "metric_definition": "db1b258e-d1d0-41b6-8751-16f601a2e230",
      "values": [
        {
          "iteration": 5432
        }
      ]
    },
    {
      "capture_id": null,
      "annotation_id": null,
      "sequence_id": "ef5610ac-9629-465f-824b-72ffddb4c488",
      "step": 0,
      "metric_definition": "db1b258e-d1d0-41b6-8751-16f601a2e230",
      "values": [
        {
          "iteration": 5433
        }
      ]
    },
    {
      "capture_id": null,
      "annotation_id": null,
      "sequence_id": "38427600-61c8-4ba1-b1f2-74659ce16efa",
      "step": 0,
      "metric_definition": "db1b258e-d1d0-41b6-8751-16f601a2e230",
      "values": [
        {
          "iteration": 5434
        }
      ]
    },
    {
      "capture_id": null,
      "annotation_id": null,
      "sequence_id": "3fe44686-3e5a-4b2b-96d4-92d74fdde00d",
      "step": 0,
      "metric_definition": "db1b258e-d1d0-41b6-8751-16f601a2e230",
      "values": [
        {
          "iteration": 5435
        }
      ]
    },
    {
      "capture_id": null,
      "annotation_id": null,
      "sequence_id": "d7d71893-f2e1-4053-b3e1-ecb86295bb18",
      "step": 0,
      "metric_definition": "db1b258e-d1d0-41b6-8751-16f601a2e230",
      "values": [
        {
          "iteration": 5436
        }
      ]
    },
    {
      "capture_id": null,
      "annotation_id": null,
      "sequence_id": "0af985ab-c540-4c3f-9946-f4b56ed5f5f9",
      "step": 0,
      "metric_definition": "db1b258e-d1d0-41b6-8751-16f601a2e230",
      "values": [
        {
          "iteration": 5437
        }
      ]
    },
    {
      "capture_id": null,
      "annotation_id": null,
      "sequence_id": "0dc96d19-105b-40ce-a2d5-835fb2b591d9",
      "step": 0,
      "metric_definition": "db1b258e-d1d0-41b6-8751-16f601a2e230",
      "values": [
        {
          "iteration": 5438
        }
      ]
    },
    {
      "capture_id": null,
      "annotation_id": null,
      "sequence_id": "fe9db562-76dc-4c88-89b0-12f802214dd7",
      "step": 0,
      "metric_definition": "db1b258e-d1d0-41b6-8751-16f601a2e230",
      "values": [
        {
          "iteration": 5439
        }
      ]
    },
    {
      "capture_id": null,
      "annotation_id": null,
      "sequence_id": "453d1e9e-fc83-470d-b7c2-5e80c03f148d",
      "step": 0,
      "metric_definition": "db1b258e-d1d0-41b6-8751-16f601a2e230",
      "values": [
        {
          "iteration": 5440
        }
      ]
    },
    {
      "capture_id": null,
      "annotation_id": null,
      "sequence_id": "ba4f8b12-0188-4729-8295-5257846e9715",
      "step": 0,
      "metric_definition": "db1b258e-d1d0-41b6-8751-16f601a2e230",
      "values": [
        {
          "iteration": 5441
        }
      ]
    },
    {
      "capture_id": null,
      "annotation_id": null,
      "sequence_id": "9300510d-b176-4fb3-8b12-922fcf2283da",
      "step": 0,
      "metric_definition": "db1b258e-d1d0-41b6-8751-16f601a2e230",
      "values": [
        {
          "iteration": 5442
        }
      ]
    },
    {
      "capture_id": null,
      "annotation_id": null,
      "sequence_id": "6aaa1841-697b-4c87-9fb5-278eebfc5ea9",
      "step": 0,
      "metric_definition": "db1b258e-d1d0-41b6-8751-16f601a2e230",
      "values": [
        {
          "iteration": 5443
        }
      ]
    },
    {
      "capture_id": null,
      "annotation_id": null,
      "sequence_id": "1bb2a036-c3c7-41f5-b1b0-ed8982eddf85",
      "step": 0,
      "metric_definition": "db1b258e-d1d0-41b6-8751-16f601a2e230",
      "values": [
        {
          "iteration": 5444
        }
      ]
    },
    {
      "capture_id": null,
      "annotation_id": null,
      "sequence_id": "fa43781a-c4be-441a-bf1e-b99df7de4ff3",
      "step": 0,
      "metric_definition": "db1b258e-d1d0-41b6-8751-16f601a2e230",
      "values": [
        {
          "iteration": 5445
        }
      ]
    },
    {
      "capture_id": null,
      "annotation_id": null,
      "sequence_id": "df056b81-de83-4c3d-84e1-eaa793bed427",
      "step": 0,
      "metric_definition": "db1b258e-d1d0-41b6-8751-16f601a2e230",
      "values": [
        {
          "iteration": 5446
        }
      ]
    },
    {
      "capture_id": null,
      "annotation_id": null,
      "sequence_id": "b87b2e5e-8cf5-4364-aa7a-465dca707ece",
      "step": 0,
      "metric_definition": "db1b258e-d1d0-41b6-8751-16f601a2e230",
      "values": [
        {
          "iteration": 5447
        }
      ]
    },
    {
      "capture_id": null,
      "annotation_id": null,
      "sequence_id": "4d61873f-097d-4b5d-8e73-d9737ba248be",
      "step": 0,
      "metric_definition": "db1b258e-d1d0-41b6-8751-16f601a2e230",
      "values": [
        {
          "iteration": 5448
        }
      ]
    },
    {
      "capture_id": null,
      "annotation_id": null,
      "sequence_id": "547ddd27-4e8c-45bd-b3bf-9588bf90a81c",
      "step": 0,
      "metric_definition": "db1b258e-d1d0-41b6-8751-16f601a2e230",
      "values": [
        {
          "iteration": 5449
        }
      ]
    },
    {
      "capture_id": null,
      "annotation_id": null,
      "sequence_id": "2baccf29-986b-47b9-a805-82790791adc8",
      "step": 0,
      "metric_definition": "db1b258e-d1d0-41b6-8751-16f601a2e230",
      "values": [
        {
          "iteration": 5450
        }
      ]
    },
    {
      "capture_id": null,
      "annotation_id": null,
      "sequence_id": "7b78107a-9005-4eec-9ad7-fb4a9e949a8c",
      "step": 0,
      "metric_definition": "db1b258e-d1d0-41b6-8751-16f601a2e230",
      "values": [
        {
          "iteration": 5451
        }
      ]
    },
    {
      "capture_id": null,
      "annotation_id": null,
      "sequence_id": "6b0e9adf-faeb-4a4a-963e-e91cecb60259",
      "step": 0,
      "metric_definition": "db1b258e-d1d0-41b6-8751-16f601a2e230",
      "values": [
        {
          "iteration": 5452
        }
      ]
    },
    {
      "capture_id": null,
      "annotation_id": null,
      "sequence_id": "9884a95c-fda4-4349-9eac-e261eaeda932",
      "step": 0,
      "metric_definition": "db1b258e-d1d0-41b6-8751-16f601a2e230",
      "values": [
        {
          "iteration": 5453
        }
      ]
    },
    {
      "capture_id": null,
      "annotation_id": null,
      "sequence_id": "399fd8b0-2c2b-4dea-b5e7-736d05d710d2",
      "step": 0,
      "metric_definition": "db1b258e-d1d0-41b6-8751-16f601a2e230",
      "values": [
        {
          "iteration": 5454
        }
      ]
    },
    {
      "capture_id": null,
      "annotation_id": null,
      "sequence_id": "071c73c1-a3b9-49f6-b1b5-74692c603e6f",
      "step": 0,
      "metric_definition": "db1b258e-d1d0-41b6-8751-16f601a2e230",
      "values": [
        {
          "iteration": 5455
        }
      ]
    },
    {
      "capture_id": null,
      "annotation_id": null,
      "sequence_id": "1d4db6c7-e4d9-45e7-be21-48472b4617f6",
      "step": 0,
      "metric_definition": "db1b258e-d1d0-41b6-8751-16f601a2e230",
      "values": [
        {
          "iteration": 5456
        }
      ]
    },
    {
      "capture_id": null,
      "annotation_id": null,
      "sequence_id": "9b988d58-262e-4376-8be3-64b74dd492f7",
      "step": 0,
      "metric_definition": "db1b258e-d1d0-41b6-8751-16f601a2e230",
      "values": [
        {
          "iteration": 5457
        }
      ]
    },
    {
      "capture_id": null,
      "annotation_id": null,
      "sequence_id": "1daa29d7-edf2-49a3-8427-618765ba8c9c",
      "step": 0,
      "metric_definition": "db1b258e-d1d0-41b6-8751-16f601a2e230",
      "values": [
        {
          "iteration": 5458
        }
      ]
    },
    {
      "capture_id": null,
      "annotation_id": null,
      "sequence_id": "3806c8b3-5da1-4034-9656-4e51ab16a152",
      "step": 0,
      "metric_definition": "db1b258e-d1d0-41b6-8751-16f601a2e230",
      "values": [
        {
          "iteration": 5459
        }
      ]
    },
    {
      "capture_id": null,
      "annotation_id": null,
      "sequence_id": "5aa58637-62a2-4d5b-9d44-8bea1ca4ae96",
      "step": 0,
      "metric_definition": "db1b258e-d1d0-41b6-8751-16f601a2e230",
      "values": [
        {
          "iteration": 5460
        }
      ]
    },
    {
      "capture_id": null,
      "annotation_id": null,
      "sequence_id": "6e765f20-270f-42d3-92a2-0b3cbfa4fbde",
      "step": 0,
      "metric_definition": "db1b258e-d1d0-41b6-8751-16f601a2e230",
      "values": [
        {
          "iteration": 5461
        }
      ]
    },
    {
      "capture_id": null,
      "annotation_id": null,
      "sequence_id": "0194c0d2-bd5f-410d-a245-46b41515461f",
      "step": 0,
      "metric_definition": "db1b258e-d1d0-41b6-8751-16f601a2e230",
      "values": [
        {
          "iteration": 5462
        }
      ]
    },
    {
      "capture_id": null,
      "annotation_id": null,
      "sequence_id": "9cb0c619-b186-46f9-af8c-494804e6a876",
      "step": 0,
      "metric_definition": "db1b258e-d1d0-41b6-8751-16f601a2e230",
      "values": [
        {
          "iteration": 5463
        }
      ]
    },
    {
      "capture_id": null,
      "annotation_id": null,
      "sequence_id": "c945c4c5-9159-472a-bd38-6ff3b7f6461f",
      "step": 0,
      "metric_definition": "db1b258e-d1d0-41b6-8751-16f601a2e230",
      "values": [
        {
          "iteration": 5464
        }
      ]
    },
    {
      "capture_id": null,
      "annotation_id": null,
      "sequence_id": "da1953f2-4acf-46e1-8953-bbffa97d32ed",
      "step": 0,
      "metric_definition": "db1b258e-d1d0-41b6-8751-16f601a2e230",
      "values": [
        {
          "iteration": 5465
        }
      ]
    },
    {
      "capture_id": null,
      "annotation_id": null,
      "sequence_id": "eea6aae6-3612-4a0e-b7cc-5ea3dce4c84a",
      "step": 0,
      "metric_definition": "db1b258e-d1d0-41b6-8751-16f601a2e230",
      "values": [
        {
          "iteration": 5466
        }
      ]
    },
    {
      "capture_id": null,
      "annotation_id": null,
      "sequence_id": "61336693-7720-4138-af03-b14a5fa5dba5",
      "step": 0,
      "metric_definition": "db1b258e-d1d0-41b6-8751-16f601a2e230",
      "values": [
        {
          "iteration": 5467
        }
      ]
    },
    {
      "capture_id": null,
      "annotation_id": null,
      "sequence_id": "26ca6748-9fb3-425b-857c-9dab8eb51cd1",
      "step": 0,
      "metric_definition": "db1b258e-d1d0-41b6-8751-16f601a2e230",
      "values": [
        {
          "iteration": 5468
        }
      ]
    },
    {
      "capture_id": null,
      "annotation_id": null,
      "sequence_id": "724943bb-e529-4611-97ff-e521ad0b398e",
      "step": 0,
      "metric_definition": "db1b258e-d1d0-41b6-8751-16f601a2e230",
      "values": [
        {
          "iteration": 5469
        }
      ]
    },
    {
      "capture_id": null,
      "annotation_id": null,
      "sequence_id": "5589ba94-7c59-4ea6-83f5-7503c697bde7",
      "step": 0,
      "metric_definition": "db1b258e-d1d0-41b6-8751-16f601a2e230",
      "values": [
        {
          "iteration": 5470
        }
      ]
    },
    {
      "capture_id": null,
      "annotation_id": null,
      "sequence_id": "a0f7c619-9f07-4a1f-a965-c48f5fe3fc20",
      "step": 0,
      "metric_definition": "db1b258e-d1d0-41b6-8751-16f601a2e230",
      "values": [
        {
          "iteration": 5471
        }
      ]
    },
    {
      "capture_id": null,
      "annotation_id": null,
      "sequence_id": "92716ea7-59dd-4197-9c39-aafdb48a867c",
      "step": 0,
      "metric_definition": "db1b258e-d1d0-41b6-8751-16f601a2e230",
      "values": [
        {
          "iteration": 5472
        }
      ]
    },
    {
      "capture_id": null,
      "annotation_id": null,
      "sequence_id": "ffb5d103-b321-4c85-88b7-a15d9bb65138",
      "step": 0,
      "metric_definition": "db1b258e-d1d0-41b6-8751-16f601a2e230",
      "values": [
        {
          "iteration": 5473
        }
      ]
    },
    {
      "capture_id": null,
      "annotation_id": null,
      "sequence_id": "b9e143d4-196f-430c-a6fd-63604faeddec",
      "step": 0,
      "metric_definition": "db1b258e-d1d0-41b6-8751-16f601a2e230",
      "values": [
        {
          "iteration": 5474
        }
      ]
    },
    {
      "capture_id": null,
      "annotation_id": null,
      "sequence_id": "e2e4cc34-46e9-4268-b17c-d0c3a713330b",
      "step": 0,
      "metric_definition": "db1b258e-d1d0-41b6-8751-16f601a2e230",
      "values": [
        {
          "iteration": 5475
        }
      ]
    },
    {
      "capture_id": null,
      "annotation_id": null,
      "sequence_id": "5852f2f2-9b2e-4d03-94dd-e6b99f818d48",
      "step": 0,
      "metric_definition": "db1b258e-d1d0-41b6-8751-16f601a2e230",
      "values": [
        {
          "iteration": 5476
        }
      ]
    },
    {
      "capture_id": null,
      "annotation_id": null,
      "sequence_id": "ddd86939-0f92-40a0-9501-ac9897ecff12",
      "step": 0,
      "metric_definition": "db1b258e-d1d0-41b6-8751-16f601a2e230",
      "values": [
        {
          "iteration": 5477
        }
      ]
    },
    {
      "capture_id": null,
      "annotation_id": null,
      "sequence_id": "d2716972-465b-44d2-ab40-9d3e3bfa975f",
      "step": 0,
      "metric_definition": "db1b258e-d1d0-41b6-8751-16f601a2e230",
      "values": [
        {
          "iteration": 5478
        }
      ]
    },
    {
      "capture_id": null,
      "annotation_id": null,
      "sequence_id": "c36624f0-5ff3-41e4-ab5d-353ab89c1b30",
      "step": 0,
      "metric_definition": "db1b258e-d1d0-41b6-8751-16f601a2e230",
      "values": [
        {
          "iteration": 5479
        }
      ]
    },
    {
      "capture_id": null,
      "annotation_id": null,
      "sequence_id": "998520bf-ec66-4add-89c6-63a7213e6aa2",
      "step": 0,
      "metric_definition": "db1b258e-d1d0-41b6-8751-16f601a2e230",
      "values": [
        {
          "iteration": 5480
        }
      ]
    },
    {
      "capture_id": null,
      "annotation_id": null,
      "sequence_id": "a31275d1-24dc-4319-88a1-6b20076bfa86",
      "step": 0,
      "metric_definition": "db1b258e-d1d0-41b6-8751-16f601a2e230",
      "values": [
        {
          "iteration": 5481
        }
      ]
    },
    {
      "capture_id": null,
      "annotation_id": null,
      "sequence_id": "dd88d26c-a9e0-4830-9126-175b884cc9f0",
      "step": 0,
      "metric_definition": "db1b258e-d1d0-41b6-8751-16f601a2e230",
      "values": [
        {
          "iteration": 5482
        }
      ]
    },
    {
      "capture_id": null,
      "annotation_id": null,
      "sequence_id": "8988f51c-189c-498c-a545-48327915c7ca",
      "step": 0,
      "metric_definition": "db1b258e-d1d0-41b6-8751-16f601a2e230",
      "values": [
        {
          "iteration": 5483
        }
      ]
    },
    {
      "capture_id": null,
      "annotation_id": null,
      "sequence_id": "446c2681-c4db-45db-8635-36dce291467b",
      "step": 0,
      "metric_definition": "db1b258e-d1d0-41b6-8751-16f601a2e230",
      "values": [
        {
          "iteration": 5484
        }
      ]
    },
    {
      "capture_id": null,
      "annotation_id": null,
      "sequence_id": "ffa0b485-dcca-4fc8-8001-7ea1c0c00a92",
      "step": 0,
      "metric_definition": "db1b258e-d1d0-41b6-8751-16f601a2e230",
      "values": [
        {
          "iteration": 5485
        }
      ]
    },
    {
      "capture_id": null,
      "annotation_id": null,
      "sequence_id": "2c30a486-1adb-4c92-b164-35169c6b707f",
      "step": 0,
      "metric_definition": "db1b258e-d1d0-41b6-8751-16f601a2e230",
      "values": [
        {
          "iteration": 5486
        }
      ]
    },
    {
      "capture_id": null,
      "annotation_id": null,
      "sequence_id": "d3fa6261-41de-47d0-9644-9729989e968e",
      "step": 0,
      "metric_definition": "db1b258e-d1d0-41b6-8751-16f601a2e230",
      "values": [
        {
          "iteration": 5487
        }
      ]
    },
    {
      "capture_id": null,
      "annotation_id": null,
      "sequence_id": "4589be34-92e4-4a20-9e32-73a147a067f8",
      "step": 0,
      "metric_definition": "db1b258e-d1d0-41b6-8751-16f601a2e230",
      "values": [
        {
          "iteration": 5488
        }
      ]
    },
    {
      "capture_id": null,
      "annotation_id": null,
      "sequence_id": "2af0b21a-07ca-4500-884e-ae6d090c36d2",
      "step": 0,
      "metric_definition": "db1b258e-d1d0-41b6-8751-16f601a2e230",
      "values": [
        {
          "iteration": 5489
        }
      ]
    },
    {
      "capture_id": null,
      "annotation_id": null,
      "sequence_id": "13408f41-20b1-4119-b7f5-d038d79e04a7",
      "step": 0,
      "metric_definition": "db1b258e-d1d0-41b6-8751-16f601a2e230",
      "values": [
        {
          "iteration": 5490
        }
      ]
    },
    {
      "capture_id": null,
      "annotation_id": null,
      "sequence_id": "ca41c8b6-8aa4-4e52-b83c-5a8fb67023a8",
      "step": 0,
      "metric_definition": "db1b258e-d1d0-41b6-8751-16f601a2e230",
      "values": [
        {
          "iteration": 5491
        }
      ]
    },
    {
      "capture_id": null,
      "annotation_id": null,
      "sequence_id": "d251da64-4edc-40fb-ae69-31c2af1b6632",
      "step": 0,
      "metric_definition": "db1b258e-d1d0-41b6-8751-16f601a2e230",
      "values": [
        {
          "iteration": 5492
        }
      ]
    },
    {
      "capture_id": null,
      "annotation_id": null,
      "sequence_id": "40273aee-7a47-4cf5-9cd8-457c86670226",
      "step": 0,
      "metric_definition": "db1b258e-d1d0-41b6-8751-16f601a2e230",
      "values": [
        {
          "iteration": 5493
        }
      ]
    },
    {
      "capture_id": null,
      "annotation_id": null,
      "sequence_id": "38f1676a-e331-4ec8-8e63-f23ec2cbc99d",
      "step": 0,
      "metric_definition": "db1b258e-d1d0-41b6-8751-16f601a2e230",
      "values": [
        {
          "iteration": 5494
        }
      ]
    },
    {
      "capture_id": null,
      "annotation_id": null,
      "sequence_id": "19bf8c6f-24b8-4650-9c81-ddf1b9687b39",
      "step": 0,
      "metric_definition": "db1b258e-d1d0-41b6-8751-16f601a2e230",
      "values": [
        {
          "iteration": 5495
        }
      ]
    },
    {
      "capture_id": null,
      "annotation_id": null,
      "sequence_id": "6c98b4da-f734-498b-aede-bc8dc0dfbd16",
      "step": 0,
      "metric_definition": "db1b258e-d1d0-41b6-8751-16f601a2e230",
      "values": [
        {
          "iteration": 5496
        }
      ]
    },
    {
      "capture_id": null,
      "annotation_id": null,
      "sequence_id": "e32d471f-3f9e-454d-b2c8-a73d5f3311ca",
      "step": 0,
      "metric_definition": "db1b258e-d1d0-41b6-8751-16f601a2e230",
      "values": [
        {
          "iteration": 5497
        }
      ]
    },
    {
      "capture_id": null,
      "annotation_id": null,
      "sequence_id": "ead898c0-08e6-4040-a31f-48e9d47ccdf3",
      "step": 0,
      "metric_definition": "db1b258e-d1d0-41b6-8751-16f601a2e230",
      "values": [
        {
          "iteration": 5498
        }
      ]
    },
    {
      "capture_id": null,
      "annotation_id": null,
      "sequence_id": "2cb574d6-3a97-4ea4-ad87-dabbaa3174e2",
      "step": 0,
      "metric_definition": "db1b258e-d1d0-41b6-8751-16f601a2e230",
      "values": [
        {
          "iteration": 5499
        }
      ]
    },
    {
      "capture_id": null,
      "annotation_id": null,
      "sequence_id": "ef96bd50-d610-4eae-acf1-3eef2ff0e651",
      "step": 0,
      "metric_definition": "db1b258e-d1d0-41b6-8751-16f601a2e230",
      "values": [
        {
          "iteration": 5500
        }
      ]
    },
    {
      "capture_id": null,
      "annotation_id": null,
      "sequence_id": "ed6122bd-43a2-4a92-baf2-37d60cebc8a4",
      "step": 0,
      "metric_definition": "db1b258e-d1d0-41b6-8751-16f601a2e230",
      "values": [
        {
          "iteration": 5501
        }
      ]
    },
    {
      "capture_id": null,
      "annotation_id": null,
      "sequence_id": "6aed3b3d-a831-4925-82e5-1ae5125a7fe0",
      "step": 0,
      "metric_definition": "db1b258e-d1d0-41b6-8751-16f601a2e230",
      "values": [
        {
          "iteration": 5502
        }
      ]
    },
    {
      "capture_id": null,
      "annotation_id": null,
      "sequence_id": "9c7a2053-a69a-46d1-af77-703b11be4e64",
      "step": 0,
      "metric_definition": "db1b258e-d1d0-41b6-8751-16f601a2e230",
      "values": [
        {
          "iteration": 5503
        }
      ]
    },
    {
      "capture_id": null,
      "annotation_id": null,
      "sequence_id": "3d041dc2-5092-4ed6-8a0d-843a2750064b",
      "step": 0,
      "metric_definition": "db1b258e-d1d0-41b6-8751-16f601a2e230",
      "values": [
        {
          "iteration": 5504
        }
      ]
    },
    {
      "capture_id": null,
      "annotation_id": null,
      "sequence_id": "62fc6da1-c02b-4f31-8017-ba65bdc65e0d",
      "step": 0,
      "metric_definition": "db1b258e-d1d0-41b6-8751-16f601a2e230",
      "values": [
        {
          "iteration": 5505
        }
      ]
    },
    {
      "capture_id": null,
      "annotation_id": null,
      "sequence_id": "ae40373e-a4d5-456e-b211-f74b19f14cd9",
      "step": 0,
      "metric_definition": "db1b258e-d1d0-41b6-8751-16f601a2e230",
      "values": [
        {
          "iteration": 5506
        }
      ]
    },
    {
      "capture_id": null,
      "annotation_id": null,
      "sequence_id": "174118f2-18c1-4615-817f-0bb8951454d3",
      "step": 0,
      "metric_definition": "db1b258e-d1d0-41b6-8751-16f601a2e230",
      "values": [
        {
          "iteration": 5507
        }
      ]
    },
    {
      "capture_id": null,
      "annotation_id": null,
      "sequence_id": "1c1fa3e6-9679-4e48-a5a6-42122834cb8c",
      "step": 0,
      "metric_definition": "db1b258e-d1d0-41b6-8751-16f601a2e230",
      "values": [
        {
          "iteration": 5508
        }
      ]
    },
    {
      "capture_id": null,
      "annotation_id": null,
      "sequence_id": "3d8159d2-448b-4e7e-aa04-5bd49a92b02d",
      "step": 0,
      "metric_definition": "db1b258e-d1d0-41b6-8751-16f601a2e230",
      "values": [
        {
          "iteration": 5509
        }
      ]
    },
    {
      "capture_id": null,
      "annotation_id": null,
      "sequence_id": "09818259-eb0b-4907-bc45-1988a685c40b",
      "step": 0,
      "metric_definition": "db1b258e-d1d0-41b6-8751-16f601a2e230",
      "values": [
        {
          "iteration": 5510
        }
      ]
    },
    {
      "capture_id": null,
      "annotation_id": null,
      "sequence_id": "876d8914-0403-4cdc-8e15-0213c6af189a",
      "step": 0,
      "metric_definition": "db1b258e-d1d0-41b6-8751-16f601a2e230",
      "values": [
        {
          "iteration": 5511
        }
      ]
    },
    {
      "capture_id": null,
      "annotation_id": null,
      "sequence_id": "60f32196-4495-4068-a19b-ce6477e7571c",
      "step": 0,
      "metric_definition": "db1b258e-d1d0-41b6-8751-16f601a2e230",
      "values": [
        {
          "iteration": 5512
        }
      ]
    },
    {
      "capture_id": null,
      "annotation_id": null,
      "sequence_id": "28e975ac-86a7-4553-97d9-05f9bacd2cad",
      "step": 0,
      "metric_definition": "db1b258e-d1d0-41b6-8751-16f601a2e230",
      "values": [
        {
          "iteration": 5513
        }
      ]
    },
    {
      "capture_id": null,
      "annotation_id": null,
      "sequence_id": "b985715b-ec01-4b0a-8279-19ed88e8402b",
      "step": 0,
      "metric_definition": "db1b258e-d1d0-41b6-8751-16f601a2e230",
      "values": [
        {
          "iteration": 5514
        }
      ]
    },
    {
      "capture_id": null,
      "annotation_id": null,
      "sequence_id": "8e45ce44-e819-45ef-bc63-b74059a5e713",
      "step": 0,
      "metric_definition": "db1b258e-d1d0-41b6-8751-16f601a2e230",
      "values": [
        {
          "iteration": 5515
        }
      ]
    },
    {
      "capture_id": null,
      "annotation_id": null,
      "sequence_id": "16f7f094-e5ce-4da9-bd36-b475e14faf61",
      "step": 0,
      "metric_definition": "db1b258e-d1d0-41b6-8751-16f601a2e230",
      "values": [
        {
          "iteration": 5516
        }
      ]
    },
    {
      "capture_id": null,
      "annotation_id": null,
      "sequence_id": "28a1c54f-fec8-49b2-955a-12ae060292c6",
      "step": 0,
      "metric_definition": "db1b258e-d1d0-41b6-8751-16f601a2e230",
      "values": [
        {
          "iteration": 5517
        }
      ]
    },
    {
      "capture_id": null,
      "annotation_id": null,
      "sequence_id": "323eba70-3a49-4c38-86d6-34270a79686a",
      "step": 0,
      "metric_definition": "db1b258e-d1d0-41b6-8751-16f601a2e230",
      "values": [
        {
          "iteration": 5518
        }
      ]
    },
    {
      "capture_id": null,
      "annotation_id": null,
      "sequence_id": "72e333fc-7993-47b9-b197-d0ef8a1b72ad",
      "step": 0,
      "metric_definition": "db1b258e-d1d0-41b6-8751-16f601a2e230",
      "values": [
        {
          "iteration": 5519
        }
      ]
    },
    {
      "capture_id": null,
      "annotation_id": null,
      "sequence_id": "3ba6a84e-7d1f-4533-8aac-75d9fd0b10d3",
      "step": 0,
      "metric_definition": "db1b258e-d1d0-41b6-8751-16f601a2e230",
      "values": [
        {
          "iteration": 5520
        }
      ]
    },
    {
      "capture_id": null,
      "annotation_id": null,
      "sequence_id": "6ddf8b67-9955-4076-acc6-6300c0f1ef45",
      "step": 0,
      "metric_definition": "db1b258e-d1d0-41b6-8751-16f601a2e230",
      "values": [
        {
          "iteration": 5521
        }
      ]
    },
    {
      "capture_id": null,
      "annotation_id": null,
      "sequence_id": "dff04920-a097-4c7b-8ebd-d24ca9097c43",
      "step": 0,
      "metric_definition": "db1b258e-d1d0-41b6-8751-16f601a2e230",
      "values": [
        {
          "iteration": 5522
        }
      ]
    },
    {
      "capture_id": null,
      "annotation_id": null,
      "sequence_id": "27810555-c078-466f-80bd-fe0c6d630e4f",
      "step": 0,
      "metric_definition": "db1b258e-d1d0-41b6-8751-16f601a2e230",
      "values": [
        {
          "iteration": 5523
        }
      ]
    },
    {
      "capture_id": null,
      "annotation_id": null,
      "sequence_id": "e579844e-1fb7-48f9-a387-290709460346",
      "step": 0,
      "metric_definition": "db1b258e-d1d0-41b6-8751-16f601a2e230",
      "values": [
        {
          "iteration": 5524
        }
      ]
    },
    {
      "capture_id": null,
      "annotation_id": null,
      "sequence_id": "afa594e9-0b4a-40c2-b3b5-3dba408e871b",
      "step": 0,
      "metric_definition": "db1b258e-d1d0-41b6-8751-16f601a2e230",
      "values": [
        {
          "iteration": 5525
        }
      ]
    },
    {
      "capture_id": null,
      "annotation_id": null,
      "sequence_id": "6a11e4c3-3839-4c49-b954-479e01399601",
      "step": 0,
      "metric_definition": "db1b258e-d1d0-41b6-8751-16f601a2e230",
      "values": [
        {
          "iteration": 5526
        }
      ]
    },
    {
      "capture_id": null,
      "annotation_id": null,
      "sequence_id": "c9a907a0-06c4-4395-ad02-30edd3b6b9db",
      "step": 0,
      "metric_definition": "db1b258e-d1d0-41b6-8751-16f601a2e230",
      "values": [
        {
          "iteration": 5527
        }
      ]
    },
    {
      "capture_id": null,
      "annotation_id": null,
      "sequence_id": "1d3b074a-87a1-4c0c-b419-c8817f47d376",
      "step": 0,
      "metric_definition": "db1b258e-d1d0-41b6-8751-16f601a2e230",
      "values": [
        {
          "iteration": 5528
        }
      ]
    },
    {
      "capture_id": null,
      "annotation_id": null,
      "sequence_id": "d8100562-b861-4a56-9a59-45d215bb33cf",
      "step": 0,
      "metric_definition": "db1b258e-d1d0-41b6-8751-16f601a2e230",
      "values": [
        {
          "iteration": 5529
        }
      ]
    },
    {
      "capture_id": null,
      "annotation_id": null,
      "sequence_id": "36f4a661-28a1-40ea-b04f-5f055293370d",
      "step": 0,
      "metric_definition": "db1b258e-d1d0-41b6-8751-16f601a2e230",
      "values": [
        {
          "iteration": 5530
        }
      ]
    },
    {
      "capture_id": null,
      "annotation_id": null,
      "sequence_id": "47316a9a-4dd7-4cc7-968e-fa4a6a03c86a",
      "step": 0,
      "metric_definition": "db1b258e-d1d0-41b6-8751-16f601a2e230",
      "values": [
        {
          "iteration": 5531
        }
      ]
    },
    {
      "capture_id": null,
      "annotation_id": null,
      "sequence_id": "5c6dd75a-4b0d-46ed-9eae-93cd80f7d2ab",
      "step": 0,
      "metric_definition": "db1b258e-d1d0-41b6-8751-16f601a2e230",
      "values": [
        {
          "iteration": 5532
        }
      ]
    },
    {
      "capture_id": null,
      "annotation_id": null,
      "sequence_id": "b3840d3a-cf91-4003-bd02-84f182a2adb6",
      "step": 0,
      "metric_definition": "db1b258e-d1d0-41b6-8751-16f601a2e230",
      "values": [
        {
          "iteration": 5533
        }
      ]
    },
    {
      "capture_id": null,
      "annotation_id": null,
      "sequence_id": "92220ae5-586e-441a-8507-8a1631d56e84",
      "step": 0,
      "metric_definition": "db1b258e-d1d0-41b6-8751-16f601a2e230",
      "values": [
        {
          "iteration": 5534
        }
      ]
    },
    {
      "capture_id": null,
      "annotation_id": null,
      "sequence_id": "7e15b99b-3ad1-46ac-94d1-2ef3e3ae3b1d",
      "step": 0,
      "metric_definition": "db1b258e-d1d0-41b6-8751-16f601a2e230",
      "values": [
        {
          "iteration": 5535
        }
      ]
    },
    {
      "capture_id": null,
      "annotation_id": null,
      "sequence_id": "fedc19a1-6c72-49f0-81d9-76604c372094",
      "step": 0,
      "metric_definition": "db1b258e-d1d0-41b6-8751-16f601a2e230",
      "values": [
        {
          "iteration": 5536
        }
      ]
    },
    {
      "capture_id": null,
      "annotation_id": null,
      "sequence_id": "c8176ad0-e040-4cb3-843d-95d06cee1d63",
      "step": 0,
      "metric_definition": "db1b258e-d1d0-41b6-8751-16f601a2e230",
      "values": [
        {
          "iteration": 5537
        }
      ]
    },
    {
      "capture_id": null,
      "annotation_id": null,
      "sequence_id": "6ed963bf-068d-4f14-a404-f6c9fd21ed28",
      "step": 0,
      "metric_definition": "db1b258e-d1d0-41b6-8751-16f601a2e230",
      "values": [
        {
          "iteration": 5538
        }
      ]
    },
    {
      "capture_id": null,
      "annotation_id": null,
      "sequence_id": "88c18523-0125-40f0-b2b4-d3a3bac6b80b",
      "step": 0,
      "metric_definition": "db1b258e-d1d0-41b6-8751-16f601a2e230",
      "values": [
        {
          "iteration": 5539
        }
      ]
    },
    {
      "capture_id": null,
      "annotation_id": null,
      "sequence_id": "34b8fde6-4c6a-4141-9f51-e79b94f0b3e4",
      "step": 0,
      "metric_definition": "db1b258e-d1d0-41b6-8751-16f601a2e230",
      "values": [
        {
          "iteration": 5540
        }
      ]
    },
    {
      "capture_id": null,
      "annotation_id": null,
      "sequence_id": "5f9c2185-998e-41b3-8687-801b46d9f417",
      "step": 0,
      "metric_definition": "db1b258e-d1d0-41b6-8751-16f601a2e230",
      "values": [
        {
          "iteration": 5541
        }
      ]
    },
    {
      "capture_id": null,
      "annotation_id": null,
      "sequence_id": "72db4174-6d1a-43ec-a1f0-c37337d193ca",
      "step": 0,
      "metric_definition": "db1b258e-d1d0-41b6-8751-16f601a2e230",
      "values": [
        {
          "iteration": 5542
        }
      ]
    },
    {
      "capture_id": null,
      "annotation_id": null,
      "sequence_id": "22997e94-bd41-4282-ab4b-c48c22ed2189",
      "step": 0,
      "metric_definition": "db1b258e-d1d0-41b6-8751-16f601a2e230",
      "values": [
        {
          "iteration": 5543
        }
      ]
    },
    {
      "capture_id": null,
      "annotation_id": null,
      "sequence_id": "2a8d8bb9-e82a-4d8b-8c50-da4051c13458",
      "step": 0,
      "metric_definition": "db1b258e-d1d0-41b6-8751-16f601a2e230",
      "values": [
        {
          "iteration": 5544
        }
      ]
    },
    {
      "capture_id": null,
      "annotation_id": null,
      "sequence_id": "631b160d-b535-424d-8df4-8bf0981ff780",
      "step": 0,
      "metric_definition": "db1b258e-d1d0-41b6-8751-16f601a2e230",
      "values": [
        {
          "iteration": 5545
        }
      ]
    },
    {
      "capture_id": null,
      "annotation_id": null,
      "sequence_id": "6e0a5e60-c4fe-439c-a6cc-51ce7edbb8f2",
      "step": 0,
      "metric_definition": "db1b258e-d1d0-41b6-8751-16f601a2e230",
      "values": [
        {
          "iteration": 5546
        }
      ]
    },
    {
      "capture_id": null,
      "annotation_id": null,
      "sequence_id": "774292a7-5a91-4522-bc44-4da7ff9214c8",
      "step": 0,
      "metric_definition": "db1b258e-d1d0-41b6-8751-16f601a2e230",
      "values": [
        {
          "iteration": 5547
        }
      ]
    },
    {
      "capture_id": null,
      "annotation_id": null,
      "sequence_id": "5dad9d30-558b-4cd6-9d0c-2ebc64912922",
      "step": 0,
      "metric_definition": "db1b258e-d1d0-41b6-8751-16f601a2e230",
      "values": [
        {
          "iteration": 5548
        }
      ]
    }
  ]
}