{
  "version": "0.0.1",
  "metrics": [
    {
      "capture_id": null,
      "annotation_id": null,
      "sequence_id": "dc660660-fde3-45ab-8ac1-a0b3a50b1345",
      "step": 0,
      "metric_definition": "db1b258e-d1d0-41b6-8751-16f601a2e230",
      "values": [
        {
          "iteration": 4499
        }
      ]
    },
    {
      "capture_id": null,
      "annotation_id": null,
      "sequence_id": "51476e50-c714-4b4e-971f-0cfd3a7eedf4",
      "step": 0,
      "metric_definition": "db1b258e-d1d0-41b6-8751-16f601a2e230",
      "values": [
        {
          "iteration": 4500
        }
      ]
    },
    {
      "capture_id": null,
      "annotation_id": null,
      "sequence_id": "18e6c654-e306-4807-8b33-2ba8295b55f5",
      "step": 0,
      "metric_definition": "db1b258e-d1d0-41b6-8751-16f601a2e230",
      "values": [
        {
          "iteration": 4501
        }
      ]
    },
    {
      "capture_id": null,
      "annotation_id": null,
      "sequence_id": "41d2a455-4920-4909-b375-079d4a485937",
      "step": 0,
      "metric_definition": "db1b258e-d1d0-41b6-8751-16f601a2e230",
      "values": [
        {
          "iteration": 4502
        }
      ]
    },
    {
      "capture_id": null,
      "annotation_id": null,
      "sequence_id": "1a6d51a1-d2e4-4df1-92d4-5a0cc4815cb8",
      "step": 0,
      "metric_definition": "db1b258e-d1d0-41b6-8751-16f601a2e230",
      "values": [
        {
          "iteration": 4503
        }
      ]
    },
    {
      "capture_id": null,
      "annotation_id": null,
      "sequence_id": "3fc66544-4408-403a-89f0-63eb5126b96f",
      "step": 0,
      "metric_definition": "db1b258e-d1d0-41b6-8751-16f601a2e230",
      "values": [
        {
          "iteration": 4504
        }
      ]
    },
    {
      "capture_id": null,
      "annotation_id": null,
      "sequence_id": "1d4a1549-5366-4a0b-9cff-19ef50150e71",
      "step": 0,
      "metric_definition": "db1b258e-d1d0-41b6-8751-16f601a2e230",
      "values": [
        {
          "iteration": 4505
        }
      ]
    },
    {
      "capture_id": null,
      "annotation_id": null,
      "sequence_id": "4884d9a7-0c4c-40c8-9a07-53dedc19a5da",
      "step": 0,
      "metric_definition": "db1b258e-d1d0-41b6-8751-16f601a2e230",
      "values": [
        {
          "iteration": 4506
        }
      ]
    },
    {
      "capture_id": null,
      "annotation_id": null,
      "sequence_id": "e41d8de2-4ec1-4fb0-a2ae-1d49aa976c84",
      "step": 0,
      "metric_definition": "db1b258e-d1d0-41b6-8751-16f601a2e230",
      "values": [
        {
          "iteration": 4507
        }
      ]
    },
    {
      "capture_id": null,
      "annotation_id": null,
      "sequence_id": "dfc22faa-d428-495c-9ff9-eb4d8453c514",
      "step": 0,
      "metric_definition": "db1b258e-d1d0-41b6-8751-16f601a2e230",
      "values": [
        {
          "iteration": 4508
        }
      ]
    },
    {
      "capture_id": null,
      "annotation_id": null,
      "sequence_id": "f48a527c-1ee8-46cd-97b4-afd1646e82e2",
      "step": 0,
      "metric_definition": "db1b258e-d1d0-41b6-8751-16f601a2e230",
      "values": [
        {
          "iteration": 4509
        }
      ]
    },
    {
      "capture_id": null,
      "annotation_id": null,
      "sequence_id": "09378f01-36b3-421a-a339-9a848da7a5ab",
      "step": 0,
      "metric_definition": "db1b258e-d1d0-41b6-8751-16f601a2e230",
      "values": [
        {
          "iteration": 4510
        }
      ]
    },
    {
      "capture_id": null,
      "annotation_id": null,
      "sequence_id": "d6300139-7674-435a-8de1-f0f8400a6fd3",
      "step": 0,
      "metric_definition": "db1b258e-d1d0-41b6-8751-16f601a2e230",
      "values": [
        {
          "iteration": 4511
        }
      ]
    },
    {
      "capture_id": null,
      "annotation_id": null,
      "sequence_id": "2c42f6eb-a86d-4d94-bad4-3d2e938796af",
      "step": 0,
      "metric_definition": "db1b258e-d1d0-41b6-8751-16f601a2e230",
      "values": [
        {
          "iteration": 4512
        }
      ]
    },
    {
      "capture_id": null,
      "annotation_id": null,
      "sequence_id": "adcbdc96-af55-43de-8291-ccccfffcd413",
      "step": 0,
      "metric_definition": "db1b258e-d1d0-41b6-8751-16f601a2e230",
      "values": [
        {
          "iteration": 4513
        }
      ]
    },
    {
      "capture_id": null,
      "annotation_id": null,
      "sequence_id": "3435977a-be69-4942-9a22-f506f762757e",
      "step": 0,
      "metric_definition": "db1b258e-d1d0-41b6-8751-16f601a2e230",
      "values": [
        {
          "iteration": 4514
        }
      ]
    },
    {
      "capture_id": null,
      "annotation_id": null,
      "sequence_id": "71f3cc6d-3471-40dd-bc69-39452e6e677c",
      "step": 0,
      "metric_definition": "db1b258e-d1d0-41b6-8751-16f601a2e230",
      "values": [
        {
          "iteration": 4515
        }
      ]
    },
    {
      "capture_id": null,
      "annotation_id": null,
      "sequence_id": "3ca465d8-4de7-402e-9889-8e3a32242575",
      "step": 0,
      "metric_definition": "db1b258e-d1d0-41b6-8751-16f601a2e230",
      "values": [
        {
          "iteration": 4516
        }
      ]
    },
    {
      "capture_id": null,
      "annotation_id": null,
      "sequence_id": "1eb22ad3-6539-4026-863c-9dcbdd75e473",
      "step": 0,
      "metric_definition": "db1b258e-d1d0-41b6-8751-16f601a2e230",
      "values": [
        {
          "iteration": 4517
        }
      ]
    },
    {
      "capture_id": null,
      "annotation_id": null,
      "sequence_id": "f565d66e-c75b-4295-b81d-830ddcaef2a5",
      "step": 0,
      "metric_definition": "db1b258e-d1d0-41b6-8751-16f601a2e230",
      "values": [
        {
          "iteration": 4518
        }
      ]
    },
    {
      "capture_id": null,
      "annotation_id": null,
      "sequence_id": "b7046806-ab3f-4b20-89b1-905bc997ce8e",
      "step": 0,
      "metric_definition": "db1b258e-d1d0-41b6-8751-16f601a2e230",
      "values": [
        {
          "iteration": 4519
        }
      ]
    },
    {
      "capture_id": null,
      "annotation_id": null,
      "sequence_id": "9f9e32b9-f5b2-4ea6-966c-37c43a173cfc",
      "step": 0,
      "metric_definition": "db1b258e-d1d0-41b6-8751-16f601a2e230",
      "values": [
        {
          "iteration": 4520
        }
      ]
    },
    {
      "capture_id": null,
      "annotation_id": null,
      "sequence_id": "f9a45ab8-7c20-4f7d-ae45-17dabf45339b",
      "step": 0,
      "metric_definition": "db1b258e-d1d0-41b6-8751-16f601a2e230",
      "values": [
        {
          "iteration": 4521
        }
      ]
    },
    {
      "capture_id": null,
      "annotation_id": null,
      "sequence_id": "f1ca8f16-c2bf-473b-bb44-d5e9e89c053d",
      "step": 0,
      "metric_definition": "db1b258e-d1d0-41b6-8751-16f601a2e230",
      "values": [
        {
          "iteration": 4522
        }
      ]
    },
    {
      "capture_id": null,
      "annotation_id": null,
      "sequence_id": "1577b0f6-c3ef-473e-ace3-1e777b493a74",
      "step": 0,
      "metric_definition": "db1b258e-d1d0-41b6-8751-16f601a2e230",
      "values": [
        {
          "iteration": 4523
        }
      ]
    },
    {
      "capture_id": null,
      "annotation_id": null,
      "sequence_id": "1e34ba79-8cbd-4362-b9fd-a692386af54b",
      "step": 0,
      "metric_definition": "db1b258e-d1d0-41b6-8751-16f601a2e230",
      "values": [
        {
          "iteration": 4524
        }
      ]
    },
    {
      "capture_id": null,
      "annotation_id": null,
      "sequence_id": "0abfe75f-71ed-48f3-b059-fd0152a96062",
      "step": 0,
      "metric_definition": "db1b258e-d1d0-41b6-8751-16f601a2e230",
      "values": [
        {
          "iteration": 4525
        }
      ]
    },
    {
      "capture_id": null,
      "annotation_id": null,
      "sequence_id": "1c06ab1a-4b76-4b08-8d3a-2a4419496c2c",
      "step": 0,
      "metric_definition": "db1b258e-d1d0-41b6-8751-16f601a2e230",
      "values": [
        {
          "iteration": 4526
        }
      ]
    },
    {
      "capture_id": null,
      "annotation_id": null,
      "sequence_id": "13de6296-27d3-4a1f-ad36-6aad97cac2e0",
      "step": 0,
      "metric_definition": "db1b258e-d1d0-41b6-8751-16f601a2e230",
      "values": [
        {
          "iteration": 4527
        }
      ]
    },
    {
      "capture_id": null,
      "annotation_id": null,
      "sequence_id": "1d6b498a-138d-422b-aa64-5ef92d590d02",
      "step": 0,
      "metric_definition": "db1b258e-d1d0-41b6-8751-16f601a2e230",
      "values": [
        {
          "iteration": 4528
        }
      ]
    },
    {
      "capture_id": null,
      "annotation_id": null,
      "sequence_id": "34827fca-eb08-4612-b6cd-234da2e1894b",
      "step": 0,
      "metric_definition": "db1b258e-d1d0-41b6-8751-16f601a2e230",
      "values": [
        {
          "iteration": 4529
        }
      ]
    },
    {
      "capture_id": null,
      "annotation_id": null,
      "sequence_id": "902a146e-1d5e-4a21-931d-b25b21034830",
      "step": 0,
      "metric_definition": "db1b258e-d1d0-41b6-8751-16f601a2e230",
      "values": [
        {
          "iteration": 4530
        }
      ]
    },
    {
      "capture_id": null,
      "annotation_id": null,
      "sequence_id": "516dbade-f1fd-4d92-98c7-b24f707b87bb",
      "step": 0,
      "metric_definition": "db1b258e-d1d0-41b6-8751-16f601a2e230",
      "values": [
        {
          "iteration": 4531
        }
      ]
    },
    {
      "capture_id": null,
      "annotation_id": null,
      "sequence_id": "fd45b8bd-09f3-432c-8518-4a17215a098d",
      "step": 0,
      "metric_definition": "db1b258e-d1d0-41b6-8751-16f601a2e230",
      "values": [
        {
          "iteration": 4532
        }
      ]
    },
    {
      "capture_id": null,
      "annotation_id": null,
      "sequence_id": "f3f5458d-4100-4cfa-a593-0d468838b815",
      "step": 0,
      "metric_definition": "db1b258e-d1d0-41b6-8751-16f601a2e230",
      "values": [
        {
          "iteration": 4533
        }
      ]
    },
    {
      "capture_id": null,
      "annotation_id": null,
      "sequence_id": "1d525ec4-2de0-478f-b31f-409ef07bfc7e",
      "step": 0,
      "metric_definition": "db1b258e-d1d0-41b6-8751-16f601a2e230",
      "values": [
        {
          "iteration": 4534
        }
      ]
    },
    {
      "capture_id": null,
      "annotation_id": null,
      "sequence_id": "03ba196d-6726-4d7f-acd7-17367a618fbb",
      "step": 0,
      "metric_definition": "db1b258e-d1d0-41b6-8751-16f601a2e230",
      "values": [
        {
          "iteration": 4535
        }
      ]
    },
    {
      "capture_id": null,
      "annotation_id": null,
      "sequence_id": "007730c6-e510-4a3b-ab03-737c6b2132c1",
      "step": 0,
      "metric_definition": "db1b258e-d1d0-41b6-8751-16f601a2e230",
      "values": [
        {
          "iteration": 4536
        }
      ]
    },
    {
      "capture_id": null,
      "annotation_id": null,
      "sequence_id": "a2865d62-ffd5-4788-a17b-bff840f8ab7c",
      "step": 0,
      "metric_definition": "db1b258e-d1d0-41b6-8751-16f601a2e230",
      "values": [
        {
          "iteration": 4537
        }
      ]
    },
    {
      "capture_id": null,
      "annotation_id": null,
      "sequence_id": "69a273f6-8e57-4657-868b-a17f139ce522",
      "step": 0,
      "metric_definition": "db1b258e-d1d0-41b6-8751-16f601a2e230",
      "values": [
        {
          "iteration": 4538
        }
      ]
    },
    {
      "capture_id": null,
      "annotation_id": null,
      "sequence_id": "b3855502-03ab-47a9-80c1-fe32d4406702",
      "step": 0,
      "metric_definition": "db1b258e-d1d0-41b6-8751-16f601a2e230",
      "values": [
        {
          "iteration": 4539
        }
      ]
    },
    {
      "capture_id": null,
      "annotation_id": null,
      "sequence_id": "2326403e-f712-4620-b203-4c9b84566c97",
      "step": 0,
      "metric_definition": "db1b258e-d1d0-41b6-8751-16f601a2e230",
      "values": [
        {
          "iteration": 4540
        }
      ]
    },
    {
      "capture_id": null,
      "annotation_id": null,
      "sequence_id": "c7e610c9-2377-4949-98bb-2256289cdd90",
      "step": 0,
      "metric_definition": "db1b258e-d1d0-41b6-8751-16f601a2e230",
      "values": [
        {
          "iteration": 4541
        }
      ]
    },
    {
      "capture_id": null,
      "annotation_id": null,
      "sequence_id": "e42ca9f8-e7fd-49b7-9d6d-faf38921d8e6",
      "step": 0,
      "metric_definition": "db1b258e-d1d0-41b6-8751-16f601a2e230",
      "values": [
        {
          "iteration": 4542
        }
      ]
    },
    {
      "capture_id": null,
      "annotation_id": null,
      "sequence_id": "0b3ff0d4-ffdb-44f7-9408-20669c2d5bc1",
      "step": 0,
      "metric_definition": "db1b258e-d1d0-41b6-8751-16f601a2e230",
      "values": [
        {
          "iteration": 4543
        }
      ]
    },
    {
      "capture_id": null,
      "annotation_id": null,
      "sequence_id": "7bb5182b-73af-422e-8eed-96794a5dba2d",
      "step": 0,
      "metric_definition": "db1b258e-d1d0-41b6-8751-16f601a2e230",
      "values": [
        {
          "iteration": 4544
        }
      ]
    },
    {
      "capture_id": null,
      "annotation_id": null,
      "sequence_id": "acd22a62-731d-4f81-a988-d58a6b79281a",
      "step": 0,
      "metric_definition": "db1b258e-d1d0-41b6-8751-16f601a2e230",
      "values": [
        {
          "iteration": 4545
        }
      ]
    },
    {
      "capture_id": null,
      "annotation_id": null,
      "sequence_id": "1b3892b2-f684-4b85-bd3e-4535db92352d",
      "step": 0,
      "metric_definition": "db1b258e-d1d0-41b6-8751-16f601a2e230",
      "values": [
        {
          "iteration": 4546
        }
      ]
    },
    {
      "capture_id": null,
      "annotation_id": null,
      "sequence_id": "86c692f0-fe30-4c51-bfdf-a9032392d407",
      "step": 0,
      "metric_definition": "db1b258e-d1d0-41b6-8751-16f601a2e230",
      "values": [
        {
          "iteration": 4547
        }
      ]
    },
    {
      "capture_id": null,
      "annotation_id": null,
      "sequence_id": "594995c8-0fb1-40dc-842a-fe586fbc5ba5",
      "step": 0,
      "metric_definition": "db1b258e-d1d0-41b6-8751-16f601a2e230",
      "values": [
        {
          "iteration": 4548
        }
      ]
    },
    {
      "capture_id": null,
      "annotation_id": null,
      "sequence_id": "3ed2522f-abb1-40be-a155-42365cff4ca4",
      "step": 0,
      "metric_definition": "db1b258e-d1d0-41b6-8751-16f601a2e230",
      "values": [
        {
          "iteration": 4549
        }
      ]
    },
    {
      "capture_id": null,
      "annotation_id": null,
      "sequence_id": "3bb14aa4-3160-467f-99ca-7714f4d3be5b",
      "step": 0,
      "metric_definition": "db1b258e-d1d0-41b6-8751-16f601a2e230",
      "values": [
        {
          "iteration": 4550
        }
      ]
    },
    {
      "capture_id": null,
      "annotation_id": null,
      "sequence_id": "5b189e7d-07c5-4b28-82c3-32499e84daa9",
      "step": 0,
      "metric_definition": "db1b258e-d1d0-41b6-8751-16f601a2e230",
      "values": [
        {
          "iteration": 4551
        }
      ]
    },
    {
      "capture_id": null,
      "annotation_id": null,
      "sequence_id": "a50bb4f1-ac74-4b99-86bb-6cd3b621f0f6",
      "step": 0,
      "metric_definition": "db1b258e-d1d0-41b6-8751-16f601a2e230",
      "values": [
        {
          "iteration": 4552
        }
      ]
    },
    {
      "capture_id": null,
      "annotation_id": null,
      "sequence_id": "e67f15a4-0fff-4c69-a591-4fd593cb9ab0",
      "step": 0,
      "metric_definition": "db1b258e-d1d0-41b6-8751-16f601a2e230",
      "values": [
        {
          "iteration": 4553
        }
      ]
    },
    {
      "capture_id": null,
      "annotation_id": null,
      "sequence_id": "0969034d-2a31-463e-9c5c-5c47406581bc",
      "step": 0,
      "metric_definition": "db1b258e-d1d0-41b6-8751-16f601a2e230",
      "values": [
        {
          "iteration": 4554
        }
      ]
    },
    {
      "capture_id": null,
      "annotation_id": null,
      "sequence_id": "bfd667e4-00c0-42a2-8f3a-1e8d1d06d8ae",
      "step": 0,
      "metric_definition": "db1b258e-d1d0-41b6-8751-16f601a2e230",
      "values": [
        {
          "iteration": 4555
        }
      ]
    },
    {
      "capture_id": null,
      "annotation_id": null,
      "sequence_id": "e52e41cb-d57a-413b-b457-6aa1160b1114",
      "step": 0,
      "metric_definition": "db1b258e-d1d0-41b6-8751-16f601a2e230",
      "values": [
        {
          "iteration": 4556
        }
      ]
    },
    {
      "capture_id": null,
      "annotation_id": null,
      "sequence_id": "ac6f7289-0b88-4959-a975-0c547ca19fc2",
      "step": 0,
      "metric_definition": "db1b258e-d1d0-41b6-8751-16f601a2e230",
      "values": [
        {
          "iteration": 4557
        }
      ]
    },
    {
      "capture_id": null,
      "annotation_id": null,
      "sequence_id": "aaf6cac4-2bd6-4e06-8319-770676539be4",
      "step": 0,
      "metric_definition": "db1b258e-d1d0-41b6-8751-16f601a2e230",
      "values": [
        {
          "iteration": 4558
        }
      ]
    },
    {
      "capture_id": null,
      "annotation_id": null,
      "sequence_id": "9afc925d-a7a5-4f08-a4e4-a95859c30863",
      "step": 0,
      "metric_definition": "db1b258e-d1d0-41b6-8751-16f601a2e230",
      "values": [
        {
          "iteration": 4559
        }
      ]
    },
    {
      "capture_id": null,
      "annotation_id": null,
      "sequence_id": "bbbc38f0-48eb-4800-82e7-a0ce4b191804",
      "step": 0,
      "metric_definition": "db1b258e-d1d0-41b6-8751-16f601a2e230",
      "values": [
        {
          "iteration": 4560
        }
      ]
    },
    {
      "capture_id": null,
      "annotation_id": null,
      "sequence_id": "bd66da74-ae69-4d79-930e-516fa06fb928",
      "step": 0,
      "metric_definition": "db1b258e-d1d0-41b6-8751-16f601a2e230",
      "values": [
        {
          "iteration": 4561
        }
      ]
    },
    {
      "capture_id": null,
      "annotation_id": null,
      "sequence_id": "a4bfdf68-3a21-4523-b3d4-5b6dd37ecd21",
      "step": 0,
      "metric_definition": "db1b258e-d1d0-41b6-8751-16f601a2e230",
      "values": [
        {
          "iteration": 4562
        }
      ]
    },
    {
      "capture_id": null,
      "annotation_id": null,
      "sequence_id": "43fe768c-7b4c-4b85-937c-7a3592e19900",
      "step": 0,
      "metric_definition": "db1b258e-d1d0-41b6-8751-16f601a2e230",
      "values": [
        {
          "iteration": 4563
        }
      ]
    },
    {
      "capture_id": null,
      "annotation_id": null,
      "sequence_id": "0415bc3b-c009-4ff8-bfc3-f549b85e8156",
      "step": 0,
      "metric_definition": "db1b258e-d1d0-41b6-8751-16f601a2e230",
      "values": [
        {
          "iteration": 4564
        }
      ]
    },
    {
      "capture_id": null,
      "annotation_id": null,
      "sequence_id": "5e7a2653-1c4d-4bae-88fe-3d8ff75bae22",
      "step": 0,
      "metric_definition": "db1b258e-d1d0-41b6-8751-16f601a2e230",
      "values": [
        {
          "iteration": 4565
        }
      ]
    },
    {
      "capture_id": null,
      "annotation_id": null,
      "sequence_id": "0c9bd376-8654-4169-ab01-f54e6bb7c18e",
      "step": 0,
      "metric_definition": "db1b258e-d1d0-41b6-8751-16f601a2e230",
      "values": [
        {
          "iteration": 4566
        }
      ]
    },
    {
      "capture_id": null,
      "annotation_id": null,
      "sequence_id": "1680fc96-8884-4d85-8db7-79b66fc8858a",
      "step": 0,
      "metric_definition": "db1b258e-d1d0-41b6-8751-16f601a2e230",
      "values": [
        {
          "iteration": 4567
        }
      ]
    },
    {
      "capture_id": null,
      "annotation_id": null,
      "sequence_id": "4cbb12a1-5cd8-4873-9563-e79d082b90b4",
      "step": 0,
      "metric_definition": "db1b258e-d1d0-41b6-8751-16f601a2e230",
      "values": [
        {
          "iteration": 4568
        }
      ]
    },
    {
      "capture_id": null,
      "annotation_id": null,
      "sequence_id": "e2c77857-594a-40f1-bc42-38d9eec17aa3",
      "step": 0,
      "metric_definition": "db1b258e-d1d0-41b6-8751-16f601a2e230",
      "values": [
        {
          "iteration": 4569
        }
      ]
    },
    {
      "capture_id": null,
      "annotation_id": null,
      "sequence_id": "82ebc7f9-466f-439d-857c-1a0f927798b4",
      "step": 0,
      "metric_definition": "db1b258e-d1d0-41b6-8751-16f601a2e230",
      "values": [
        {
          "iteration": 4570
        }
      ]
    },
    {
      "capture_id": null,
      "annotation_id": null,
      "sequence_id": "46ef1c28-8c28-4dc6-8e3d-bf2012faa932",
      "step": 0,
      "metric_definition": "db1b258e-d1d0-41b6-8751-16f601a2e230",
      "values": [
        {
          "iteration": 4571
        }
      ]
    },
    {
      "capture_id": null,
      "annotation_id": null,
      "sequence_id": "9c1b0e05-39a6-4abf-8feb-a0356ea9b16c",
      "step": 0,
      "metric_definition": "db1b258e-d1d0-41b6-8751-16f601a2e230",
      "values": [
        {
          "iteration": 4572
        }
      ]
    },
    {
      "capture_id": null,
      "annotation_id": null,
      "sequence_id": "95390b60-6d97-4cdb-9297-297a337efeaa",
      "step": 0,
      "metric_definition": "db1b258e-d1d0-41b6-8751-16f601a2e230",
      "values": [
        {
          "iteration": 4573
        }
      ]
    },
    {
      "capture_id": null,
      "annotation_id": null,
      "sequence_id": "4e446aa6-6a13-4169-808c-1cb1470b64a1",
      "step": 0,
      "metric_definition": "db1b258e-d1d0-41b6-8751-16f601a2e230",
      "values": [
        {
          "iteration": 4574
        }
      ]
    },
    {
      "capture_id": null,
      "annotation_id": null,
      "sequence_id": "16c395a9-cd00-4afb-bc8e-c8fa6a684a43",
      "step": 0,
      "metric_definition": "db1b258e-d1d0-41b6-8751-16f601a2e230",
      "values": [
        {
          "iteration": 4575
        }
      ]
    },
    {
      "capture_id": null,
      "annotation_id": null,
      "sequence_id": "a3da348b-8471-482d-a47a-05d0ff37cb87",
      "step": 0,
      "metric_definition": "db1b258e-d1d0-41b6-8751-16f601a2e230",
      "values": [
        {
          "iteration": 4576
        }
      ]
    },
    {
      "capture_id": null,
      "annotation_id": null,
      "sequence_id": "ef9d4c65-b00c-48cd-87d2-75fc65b0a975",
      "step": 0,
      "metric_definition": "db1b258e-d1d0-41b6-8751-16f601a2e230",
      "values": [
        {
          "iteration": 4577
        }
      ]
    },
    {
      "capture_id": null,
      "annotation_id": null,
      "sequence_id": "d65c5905-60d6-4cb0-9d78-3757053be0a7",
      "step": 0,
      "metric_definition": "db1b258e-d1d0-41b6-8751-16f601a2e230",
      "values": [
        {
          "iteration": 4578
        }
      ]
    },
    {
      "capture_id": null,
      "annotation_id": null,
      "sequence_id": "5000e5cf-1692-48b2-aae4-fc1f7b7a2f8f",
      "step": 0,
      "metric_definition": "db1b258e-d1d0-41b6-8751-16f601a2e230",
      "values": [
        {
          "iteration": 4579
        }
      ]
    },
    {
      "capture_id": null,
      "annotation_id": null,
      "sequence_id": "ec186b8a-b4d4-4da3-af01-e195d1a06633",
      "step": 0,
      "metric_definition": "db1b258e-d1d0-41b6-8751-16f601a2e230",
      "values": [
        {
          "iteration": 4580
        }
      ]
    },
    {
      "capture_id": null,
      "annotation_id": null,
      "sequence_id": "6e23cfa6-dc89-41b2-804c-a7307d22463b",
      "step": 0,
      "metric_definition": "db1b258e-d1d0-41b6-8751-16f601a2e230",
      "values": [
        {
          "iteration": 4581
        }
      ]
    },
    {
      "capture_id": null,
      "annotation_id": null,
      "sequence_id": "24c4595d-c6ac-4cc9-b052-4b98fb1d974c",
      "step": 0,
      "metric_definition": "db1b258e-d1d0-41b6-8751-16f601a2e230",
      "values": [
        {
          "iteration": 4582
        }
      ]
    },
    {
      "capture_id": null,
      "annotation_id": null,
      "sequence_id": "a3dd1a92-b70d-4858-b939-fdda2b549544",
      "step": 0,
      "metric_definition": "db1b258e-d1d0-41b6-8751-16f601a2e230",
      "values": [
        {
          "iteration": 4583
        }
      ]
    },
    {
      "capture_id": null,
      "annotation_id": null,
      "sequence_id": "6e42fa63-0cfb-445f-88a5-dffbf0238a0b",
      "step": 0,
      "metric_definition": "db1b258e-d1d0-41b6-8751-16f601a2e230",
      "values": [
        {
          "iteration": 4584
        }
      ]
    },
    {
      "capture_id": null,
      "annotation_id": null,
      "sequence_id": "7e1103fc-668a-45f8-8fdd-7375a1c65255",
      "step": 0,
      "metric_definition": "db1b258e-d1d0-41b6-8751-16f601a2e230",
      "values": [
        {
          "iteration": 4585
        }
      ]
    },
    {
      "capture_id": null,
      "annotation_id": null,
      "sequence_id": "36e0cece-c21a-4185-a14a-f74556a9600b",
      "step": 0,
      "metric_definition": "db1b258e-d1d0-41b6-8751-16f601a2e230",
      "values": [
        {
          "iteration": 4586
        }
      ]
    },
    {
      "capture_id": null,
      "annotation_id": null,
      "sequence_id": "8513d0f7-fdd8-4d35-9a08-69609bb16337",
      "step": 0,
      "metric_definition": "db1b258e-d1d0-41b6-8751-16f601a2e230",
      "values": [
        {
          "iteration": 4587
        }
      ]
    },
    {
      "capture_id": null,
      "annotation_id": null,
      "sequence_id": "714f345c-c231-4911-a64d-008c4cfa519a",
      "step": 0,
      "metric_definition": "db1b258e-d1d0-41b6-8751-16f601a2e230",
      "values": [
        {
          "iteration": 4588
        }
      ]
    },
    {
      "capture_id": null,
      "annotation_id": null,
      "sequence_id": "732ad910-0f8f-4881-a133-8115fd940d23",
      "step": 0,
      "metric_definition": "db1b258e-d1d0-41b6-8751-16f601a2e230",
      "values": [
        {
          "iteration": 4589
        }
      ]
    },
    {
      "capture_id": null,
      "annotation_id": null,
      "sequence_id": "809e2bb7-8fc9-4fdb-940c-9649694d1eff",
      "step": 0,
      "metric_definition": "db1b258e-d1d0-41b6-8751-16f601a2e230",
      "values": [
        {
          "iteration": 4590
        }
      ]
    },
    {
      "capture_id": null,
      "annotation_id": null,
      "sequence_id": "79951ceb-521c-4b28-9829-30d94bce486b",
      "step": 0,
      "metric_definition": "db1b258e-d1d0-41b6-8751-16f601a2e230",
      "values": [
        {
          "iteration": 4591
        }
      ]
    },
    {
      "capture_id": null,
      "annotation_id": null,
      "sequence_id": "2c05e9d1-1f74-429a-b8c6-9a314c630d2e",
      "step": 0,
      "metric_definition": "db1b258e-d1d0-41b6-8751-16f601a2e230",
      "values": [
        {
          "iteration": 4592
        }
      ]
    },
    {
      "capture_id": null,
      "annotation_id": null,
      "sequence_id": "6062b77a-26b3-46a7-94e1-30345c2e9117",
      "step": 0,
      "metric_definition": "db1b258e-d1d0-41b6-8751-16f601a2e230",
      "values": [
        {
          "iteration": 4593
        }
      ]
    },
    {
      "capture_id": null,
      "annotation_id": null,
      "sequence_id": "505c5314-fb55-4e9a-8a8d-d91055de371f",
      "step": 0,
      "metric_definition": "db1b258e-d1d0-41b6-8751-16f601a2e230",
      "values": [
        {
          "iteration": 4594
        }
      ]
    },
    {
      "capture_id": null,
      "annotation_id": null,
      "sequence_id": "e26beb93-204f-4315-94d0-189f26fccb96",
      "step": 0,
      "metric_definition": "db1b258e-d1d0-41b6-8751-16f601a2e230",
      "values": [
        {
          "iteration": 4595
        }
      ]
    },
    {
      "capture_id": null,
      "annotation_id": null,
      "sequence_id": "fa43541a-ae6b-4c5b-84f9-82e3566f57bb",
      "step": 0,
      "metric_definition": "db1b258e-d1d0-41b6-8751-16f601a2e230",
      "values": [
        {
          "iteration": 4596
        }
      ]
    },
    {
      "capture_id": null,
      "annotation_id": null,
      "sequence_id": "a533c726-4201-4a86-89ec-024536d5eaca",
      "step": 0,
      "metric_definition": "db1b258e-d1d0-41b6-8751-16f601a2e230",
      "values": [
        {
          "iteration": 4597
        }
      ]
    },
    {
      "capture_id": null,
      "annotation_id": null,
      "sequence_id": "11c82976-7cd1-4994-abab-a2b16460866f",
      "step": 0,
      "metric_definition": "db1b258e-d1d0-41b6-8751-16f601a2e230",
      "values": [
        {
          "iteration": 4598
        }
      ]
    },
    {
      "capture_id": null,
      "annotation_id": null,
      "sequence_id": "43cce04b-fe76-46d8-8d48-b3b141fd1efc",
      "step": 0,
      "metric_definition": "db1b258e-d1d0-41b6-8751-16f601a2e230",
      "values": [
        {
          "iteration": 4599
        }
      ]
    },
    {
      "capture_id": null,
      "annotation_id": null,
      "sequence_id": "3775c091-8633-4657-857b-3fbfeb8cd010",
      "step": 0,
      "metric_definition": "db1b258e-d1d0-41b6-8751-16f601a2e230",
      "values": [
        {
          "iteration": 4600
        }
      ]
    },
    {
      "capture_id": null,
      "annotation_id": null,
      "sequence_id": "350702dd-3cef-471c-9c74-9c1b5fe647ba",
      "step": 0,
      "metric_definition": "db1b258e-d1d0-41b6-8751-16f601a2e230",
      "values": [
        {
          "iteration": 4601
        }
      ]
    },
    {
      "capture_id": null,
      "annotation_id": null,
      "sequence_id": "03c97bbe-a7a5-4649-8380-8c595878ccc2",
      "step": 0,
      "metric_definition": "db1b258e-d1d0-41b6-8751-16f601a2e230",
      "values": [
        {
          "iteration": 4602
        }
      ]
    },
    {
      "capture_id": null,
      "annotation_id": null,
      "sequence_id": "3d0791e3-bf7f-42f8-8ad9-d69f6550460c",
      "step": 0,
      "metric_definition": "db1b258e-d1d0-41b6-8751-16f601a2e230",
      "values": [
        {
          "iteration": 4603
        }
      ]
    },
    {
      "capture_id": null,
      "annotation_id": null,
      "sequence_id": "4fe01463-21a6-4950-9f2d-a8f04720054b",
      "step": 0,
      "metric_definition": "db1b258e-d1d0-41b6-8751-16f601a2e230",
      "values": [
        {
          "iteration": 4604
        }
      ]
    },
    {
      "capture_id": null,
      "annotation_id": null,
      "sequence_id": "b8b19a77-2140-41ec-8257-cb6a4631cf42",
      "step": 0,
      "metric_definition": "db1b258e-d1d0-41b6-8751-16f601a2e230",
      "values": [
        {
          "iteration": 4605
        }
      ]
    },
    {
      "capture_id": null,
      "annotation_id": null,
      "sequence_id": "94321a4c-3968-41fb-a757-519c7f321564",
      "step": 0,
      "metric_definition": "db1b258e-d1d0-41b6-8751-16f601a2e230",
      "values": [
        {
          "iteration": 4606
        }
      ]
    },
    {
      "capture_id": null,
      "annotation_id": null,
      "sequence_id": "19ddafec-1fc7-499c-b9d5-218797844195",
      "step": 0,
      "metric_definition": "db1b258e-d1d0-41b6-8751-16f601a2e230",
      "values": [
        {
          "iteration": 4607
        }
      ]
    },
    {
      "capture_id": null,
      "annotation_id": null,
      "sequence_id": "0d792b66-c3a8-4e06-852e-b728591e825c",
      "step": 0,
      "metric_definition": "db1b258e-d1d0-41b6-8751-16f601a2e230",
      "values": [
        {
          "iteration": 4608
        }
      ]
    },
    {
      "capture_id": null,
      "annotation_id": null,
      "sequence_id": "0d4aca78-5783-4df4-a9ee-6afdf5541023",
      "step": 0,
      "metric_definition": "db1b258e-d1d0-41b6-8751-16f601a2e230",
      "values": [
        {
          "iteration": 4609
        }
      ]
    },
    {
      "capture_id": null,
      "annotation_id": null,
      "sequence_id": "1aef35df-2041-440f-88df-1788bb538479",
      "step": 0,
      "metric_definition": "db1b258e-d1d0-41b6-8751-16f601a2e230",
      "values": [
        {
          "iteration": 4610
        }
      ]
    },
    {
      "capture_id": null,
      "annotation_id": null,
      "sequence_id": "f9dca11b-1c54-4723-9b52-e6557fd69121",
      "step": 0,
      "metric_definition": "db1b258e-d1d0-41b6-8751-16f601a2e230",
      "values": [
        {
          "iteration": 4611
        }
      ]
    },
    {
      "capture_id": null,
      "annotation_id": null,
      "sequence_id": "351762af-5095-41cf-8dc9-eeab72f5b5ec",
      "step": 0,
      "metric_definition": "db1b258e-d1d0-41b6-8751-16f601a2e230",
      "values": [
        {
          "iteration": 4612
        }
      ]
    },
    {
      "capture_id": null,
      "annotation_id": null,
      "sequence_id": "e92f275d-d9cf-4f5e-8225-4326ddc21553",
      "step": 0,
      "metric_definition": "db1b258e-d1d0-41b6-8751-16f601a2e230",
      "values": [
        {
          "iteration": 4613
        }
      ]
    },
    {
      "capture_id": null,
      "annotation_id": null,
      "sequence_id": "f3801935-79d3-4220-9ab9-51949bd33522",
      "step": 0,
      "metric_definition": "db1b258e-d1d0-41b6-8751-16f601a2e230",
      "values": [
        {
          "iteration": 4614
        }
      ]
    },
    {
      "capture_id": null,
      "annotation_id": null,
      "sequence_id": "15a17096-e1ef-4d87-9a11-c09d2387b7f1",
      "step": 0,
      "metric_definition": "db1b258e-d1d0-41b6-8751-16f601a2e230",
      "values": [
        {
          "iteration": 4615
        }
      ]
    },
    {
      "capture_id": null,
      "annotation_id": null,
      "sequence_id": "ed8e3b7c-af8c-4a44-b984-b7b814d1c576",
      "step": 0,
      "metric_definition": "db1b258e-d1d0-41b6-8751-16f601a2e230",
      "values": [
        {
          "iteration": 4616
        }
      ]
    },
    {
      "capture_id": null,
      "annotation_id": null,
      "sequence_id": "10a6cefd-8221-48f9-8e82-69d54a19e96b",
      "step": 0,
      "metric_definition": "db1b258e-d1d0-41b6-8751-16f601a2e230",
      "values": [
        {
          "iteration": 4617
        }
      ]
    },
    {
      "capture_id": null,
      "annotation_id": null,
      "sequence_id": "af80b1b2-20e2-4a8d-a87b-7d7372b70c97",
      "step": 0,
      "metric_definition": "db1b258e-d1d0-41b6-8751-16f601a2e230",
      "values": [
        {
          "iteration": 4618
        }
      ]
    },
    {
      "capture_id": null,
      "annotation_id": null,
      "sequence_id": "00dd8c09-fb54-4bc5-a315-adb42c10c3f4",
      "step": 0,
      "metric_definition": "db1b258e-d1d0-41b6-8751-16f601a2e230",
      "values": [
        {
          "iteration": 4619
        }
      ]
    },
    {
      "capture_id": null,
      "annotation_id": null,
      "sequence_id": "2e8184e5-b413-40a1-a6bf-389a3dc933a1",
      "step": 0,
      "metric_definition": "db1b258e-d1d0-41b6-8751-16f601a2e230",
      "values": [
        {
          "iteration": 4620
        }
      ]
    },
    {
      "capture_id": null,
      "annotation_id": null,
      "sequence_id": "664b6c40-4b77-4d40-9990-8d094122f9d0",
      "step": 0,
      "metric_definition": "db1b258e-d1d0-41b6-8751-16f601a2e230",
      "values": [
        {
          "iteration": 4621
        }
      ]
    },
    {
      "capture_id": null,
      "annotation_id": null,
      "sequence_id": "5d417155-1cb0-4da3-a8b4-226519bc2445",
      "step": 0,
      "metric_definition": "db1b258e-d1d0-41b6-8751-16f601a2e230",
      "values": [
        {
          "iteration": 4622
        }
      ]
    },
    {
      "capture_id": null,
      "annotation_id": null,
      "sequence_id": "68887775-85d9-43a2-9041-034403e8f4f8",
      "step": 0,
      "metric_definition": "db1b258e-d1d0-41b6-8751-16f601a2e230",
      "values": [
        {
          "iteration": 4623
        }
      ]
    },
    {
      "capture_id": null,
      "annotation_id": null,
      "sequence_id": "bd3806c4-ab33-4d33-92c1-d12f08e11126",
      "step": 0,
      "metric_definition": "db1b258e-d1d0-41b6-8751-16f601a2e230",
      "values": [
        {
          "iteration": 4624
        }
      ]
    },
    {
      "capture_id": null,
      "annotation_id": null,
      "sequence_id": "16b6bc43-fb27-43db-a1fe-815c8cb2842c",
      "step": 0,
      "metric_definition": "db1b258e-d1d0-41b6-8751-16f601a2e230",
      "values": [
        {
          "iteration": 4625
        }
      ]
    },
    {
      "capture_id": null,
      "annotation_id": null,
      "sequence_id": "e06e1ea4-ac86-475f-b3a5-1cbea265cf76",
      "step": 0,
      "metric_definition": "db1b258e-d1d0-41b6-8751-16f601a2e230",
      "values": [
        {
          "iteration": 4626
        }
      ]
    },
    {
      "capture_id": null,
      "annotation_id": null,
      "sequence_id": "dbfe1413-39bf-4280-a2ab-8ad9e7ee2307",
      "step": 0,
      "metric_definition": "db1b258e-d1d0-41b6-8751-16f601a2e230",
      "values": [
        {
          "iteration": 4627
        }
      ]
    },
    {
      "capture_id": null,
      "annotation_id": null,
      "sequence_id": "752b786c-2015-40fd-85a3-9eb99c7e18a8",
      "step": 0,
      "metric_definition": "db1b258e-d1d0-41b6-8751-16f601a2e230",
      "values": [
        {
          "iteration": 4628
        }
      ]
    },
    {
      "capture_id": null,
      "annotation_id": null,
      "sequence_id": "295ac6c2-df28-4c95-8103-527680fd02bd",
      "step": 0,
      "metric_definition": "db1b258e-d1d0-41b6-8751-16f601a2e230",
      "values": [
        {
          "iteration": 4629
        }
      ]
    },
    {
      "capture_id": null,
      "annotation_id": null,
      "sequence_id": "e3ad0952-1b0d-4208-8f0a-906bac44235c",
      "step": 0,
      "metric_definition": "db1b258e-d1d0-41b6-8751-16f601a2e230",
      "values": [
        {
          "iteration": 4630
        }
      ]
    },
    {
      "capture_id": null,
      "annotation_id": null,
      "sequence_id": "586923b5-f23f-4129-b614-533f3d4f937b",
      "step": 0,
      "metric_definition": "db1b258e-d1d0-41b6-8751-16f601a2e230",
      "values": [
        {
          "iteration": 4631
        }
      ]
    },
    {
      "capture_id": null,
      "annotation_id": null,
      "sequence_id": "4bcd4bc0-6e83-4689-8b73-f8acf36db7c3",
      "step": 0,
      "metric_definition": "db1b258e-d1d0-41b6-8751-16f601a2e230",
      "values": [
        {
          "iteration": 4632
        }
      ]
    },
    {
      "capture_id": null,
      "annotation_id": null,
      "sequence_id": "57a80f20-b35d-4c57-8ad1-4d739d3c3227",
      "step": 0,
      "metric_definition": "db1b258e-d1d0-41b6-8751-16f601a2e230",
      "values": [
        {
          "iteration": 4633
        }
      ]
    },
    {
      "capture_id": null,
      "annotation_id": null,
      "sequence_id": "f1c6418a-75af-4d76-8701-684b9ddf7af2",
      "step": 0,
      "metric_definition": "db1b258e-d1d0-41b6-8751-16f601a2e230",
      "values": [
        {
          "iteration": 4634
        }
      ]
    },
    {
      "capture_id": null,
      "annotation_id": null,
      "sequence_id": "511609e2-fdf1-4217-8604-1bcba7458148",
      "step": 0,
      "metric_definition": "db1b258e-d1d0-41b6-8751-16f601a2e230",
      "values": [
        {
          "iteration": 4635
        }
      ]
    },
    {
      "capture_id": null,
      "annotation_id": null,
      "sequence_id": "5fee38fe-2815-4d1d-abe0-5271f54ae1f2",
      "step": 0,
      "metric_definition": "db1b258e-d1d0-41b6-8751-16f601a2e230",
      "values": [
        {
          "iteration": 4636
        }
      ]
    },
    {
      "capture_id": null,
      "annotation_id": null,
      "sequence_id": "0a71bbbc-ec62-43b2-932f-c9a99ffb3c11",
      "step": 0,
      "metric_definition": "db1b258e-d1d0-41b6-8751-16f601a2e230",
      "values": [
        {
          "iteration": 4637
        }
      ]
    },
    {
      "capture_id": null,
      "annotation_id": null,
      "sequence_id": "753a98e4-c452-413b-95c6-af4c74715422",
      "step": 0,
      "metric_definition": "db1b258e-d1d0-41b6-8751-16f601a2e230",
      "values": [
        {
          "iteration": 4638
        }
      ]
    },
    {
      "capture_id": null,
      "annotation_id": null,
      "sequence_id": "2063bc42-2dd2-4f94-b579-7229350ca733",
      "step": 0,
      "metric_definition": "db1b258e-d1d0-41b6-8751-16f601a2e230",
      "values": [
        {
          "iteration": 4639
        }
      ]
    },
    {
      "capture_id": null,
      "annotation_id": null,
      "sequence_id": "eb12536a-1f46-41c8-845d-c051e09d8034",
      "step": 0,
      "metric_definition": "db1b258e-d1d0-41b6-8751-16f601a2e230",
      "values": [
        {
          "iteration": 4640
        }
      ]
    },
    {
      "capture_id": null,
      "annotation_id": null,
      "sequence_id": "7a12a69b-7e39-4865-b924-f738817dadf5",
      "step": 0,
      "metric_definition": "db1b258e-d1d0-41b6-8751-16f601a2e230",
      "values": [
        {
          "iteration": 4641
        }
      ]
    },
    {
      "capture_id": null,
      "annotation_id": null,
      "sequence_id": "b94c4734-6b5a-46b9-b5e6-1472c19ca976",
      "step": 0,
      "metric_definition": "db1b258e-d1d0-41b6-8751-16f601a2e230",
      "values": [
        {
          "iteration": 4642
        }
      ]
    },
    {
      "capture_id": null,
      "annotation_id": null,
      "sequence_id": "949ee61d-7805-449e-9b4a-7baf09253b2e",
      "step": 0,
      "metric_definition": "db1b258e-d1d0-41b6-8751-16f601a2e230",
      "values": [
        {
          "iteration": 4643
        }
      ]
    },
    {
      "capture_id": null,
      "annotation_id": null,
      "sequence_id": "9d11eb78-2c5b-4af4-ac12-87c878a70870",
      "step": 0,
      "metric_definition": "db1b258e-d1d0-41b6-8751-16f601a2e230",
      "values": [
        {
          "iteration": 4644
        }
      ]
    },
    {
      "capture_id": null,
      "annotation_id": null,
      "sequence_id": "32209dfe-faae-434d-80bc-bf4f777c2663",
      "step": 0,
      "metric_definition": "db1b258e-d1d0-41b6-8751-16f601a2e230",
      "values": [
        {
          "iteration": 4645
        }
      ]
    },
    {
      "capture_id": null,
      "annotation_id": null,
      "sequence_id": "9d5a4d8f-3da2-43fc-a3b8-c2c1dcad2a45",
      "step": 0,
      "metric_definition": "db1b258e-d1d0-41b6-8751-16f601a2e230",
      "values": [
        {
          "iteration": 4646
        }
      ]
    },
    {
      "capture_id": null,
      "annotation_id": null,
      "sequence_id": "4922251e-5f43-4338-b728-7c33be8020c2",
      "step": 0,
      "metric_definition": "db1b258e-d1d0-41b6-8751-16f601a2e230",
      "values": [
        {
          "iteration": 4647
        }
      ]
    },
    {
      "capture_id": null,
      "annotation_id": null,
      "sequence_id": "f2331bad-2484-4a32-b431-06a89000d430",
      "step": 0,
      "metric_definition": "db1b258e-d1d0-41b6-8751-16f601a2e230",
      "values": [
        {
          "iteration": 4648
        }
      ]
    }
  ]
}